blizzapi/__init__.py
blizzapi/clients/__init__.py
blizzapi/clients/wow/classic_client.py
blizzapi/clients/wow/classic_era_client.py
blizzapi/clients/wow/retail_client.py
blizzapi/core/base_client.py
blizzapi/core/constants.py
blizzapi/core/enums.py
blizzapi/core/fetch.py
blizzapi/core/oauth2_client.py
blizzapi/core/utils.py
blizzapi-1.0.6.dist-info/licenses/LICENSE
blizzapi-1.0.6.dist-info/METADATA
blizzapi-1.0.6.dist-info/WHEEL
blizzapi-1.0.6.dist-info/top_level.txt
blizzapi-1.0.6.dist-info/RECORD
