Metadata-Version: 2.4
Name: blizzapi
Version: 1.0.6
Summary: Python package to connect to the blizzard API.
Author-email: Nick Stuer <nickstuer@duck.com>
Project-URL: Homepage, https://github.com/nickstuer/blizzapi
Project-URL: Issues, https://github.com/nickstuer/blizzapi/issues
Classifier: Programming Language :: Python :: 3
Classifier: License :: OSI Approved :: MIT License
Classifier: Operating System :: OS Independent
Classifier: Development Status :: 5 - Production/Stable
Requires-Python: >=3.10
License-File: LICENSE
Requires-Dist: requests-oauthlib>=2.0.0
Dynamic: license-file
